argus_gui/__init__.py
argus_gui/colors.py
argus_gui/frameFinderPyglet.py
argus_gui/graphers.py
argus_gui/gui.py
argus_gui/logger.py
argus_gui/output.py
argus_gui/patterns.py
argus_gui/sbaDriver.py
argus_gui/sync.py
argus_gui/tools.py
argus_gui/triangulate.py
argus_gui/undistort.py
argus_gui/version.py
argus_gui/resources/LICENSE.txt
argus_gui/resources/__init__.py
argus_gui/resources/calib-gui-paddings.txt
argus_gui/resources/dwarp-gui-paddings.txt
argus_gui/resources/libsba.dll
argus_gui/resources/libsba.dylib
argus_gui/resources/libsba.so
argus_gui/resources/libsba_p3.dll
argus_gui/resources/libsbaprojs.dll
argus_gui/resources/libsbaprojs.dylib
argus_gui/resources/libsbaprojs.so
argus_gui/resources/libsbaprojs_p3.dll
argus_gui/resources/patterns-gui-paddings.txt
argus_gui/resources/sba_lib_sources.tar.gz
argus_gui/resources/sync-gui-paddings.txt
argus_gui/resources/calibrations/Default Camera Model.csv
argus_gui/resources/calibrations/GoPro Hero3 Black.csv
argus_gui/resources/calibrations/GoPro Hero3 White.csv
argus_gui/resources/calibrations/GoPro Hero4 Black.csv
argus_gui/resources/calibrations/GoPro Hero4 Silver.csv
argus_gui/resources/calibrations/readme.txt
argus_gui/resources/icons/aperture-8x.gif
argus_gui/resources/icons/calculator-8x.gif
argus_gui/resources/icons/eye-8x.gif
argus_gui/resources/icons/grid-four-up-8x.gif
argus_gui/resources/icons/location-8x.gif
argus_gui/resources/icons/pulse-8x.gif
argus_gui/resources/icons/wand.gif
argus_gui/resources/scripts/Argus
argus_gui/resources/scripts/Argus_win.py
argus_gui/resources/scripts/argus-calibrate
argus_gui/resources/scripts/argus-click
argus_gui/resources/scripts/argus-dwarp
argus_gui/resources/scripts/argus-log
argus_gui/resources/scripts/argus-patterns
argus_gui/resources/scripts/argus-show
argus_gui/resources/scripts/argus-sync
argus_gui/resources/scripts/argus-wand
argus_gui-2.1.dev3.data/scripts/Argus
argus_gui-2.1.dev3.dist-info/DESCRIPTION.rst
argus_gui-2.1.dev3.dist-info/METADATA
argus_gui-2.1.dev3.dist-info/RECORD
argus_gui-2.1.dev3.dist-info/WHEEL
argus_gui-2.1.dev3.dist-info/dependency_links.txt
argus_gui-2.1.dev3.dist-info/metadata.json
argus_gui-2.1.dev3.dist-info/top_level.txt
