Metadata-Version: 2.0
Name: argus-gui
Version: 2.1.dev3
Summary: Tools for 3D camera calibration and reconstruction with graphical user interfaces
Home-page: http://argus.web.unc.edu
Author: Dylan Ray and Dennis Evangelista
Author-email: ddray1993@gmail.com
License: GNU GPLv3
Keywords: calibration,camera,camera calibration,photogrammetry
Platform: UNKNOWN
Classifier: Development Status :: 3 - Alpha
Classifier: Intended Audience :: Science/Research
Classifier: License :: OSI Approved :: GNU General Public License v3 (GPLv3)
Classifier: Operating System :: OS Independent
Classifier: Operating System :: POSIX :: Linux
Classifier: Programming Language :: Python :: 2.7
Classifier: Topic :: Multimedia :: Graphics
Classifier: Topic :: Multimedia :: Graphics :: 3D Modeling
Classifier: Topic :: Multimedia :: Graphics :: Capture :: Digital Camera
Classifier: Topic :: Multimedia :: Video
Classifier: Topic :: Scientific/Engineering
Requires-Dist: numpy (>=1.9.1)
Requires-Dist: pandas (>=0.15.2)
Requires-Dist: matplotlib (>=1.3.1)
Requires-Dist: pyglet (>=1.2.4)
Requires-Dist: moviepy (>=0.2.2.11)
Requires-Dist: Pmw (>=1.3.3)
Requires-Dist: texttable (>=0.8.3)
Requires-Dist: pygarrayimage (>=1.0)
Requires-Dist: sba (>=1.6.5.1)
Requires-Dist: audioread (>=2.1.1)
Requires-Dist: psutil (>=3.4.1)
Requires-Dist: argus (>=0.0.6)
Requires-Dist: pykalman
Requires-Dist: future (>=0.16.0)
